yousif_raiyan_pip_package/__init__.py
yousif_raiyan_pip_package/analyzer.py
yousif_raiyan_pip_package/connectivity_analyzer.py
yousif_raiyan_pip_package/edf_loader.py
yousif_raiyan_pip_package/eeg_graph_representation.py
yousif_raiyan_pip_package/fooof_analyzer.py
yousif_raiyan_pip_package/good_bad_classes.npy
yousif_raiyan_pip_package/logreg_good_bad.pkl
yousif_raiyan_pip_package/spectral_analyzer.py
yousif_raiyan_pip_package/trigger_detector.py
yousif_raiyan_pip_package-1.8.6.dist-info/licenses/LICENSE
yousif_raiyan_pip_package-1.8.6.dist-info/METADATA
yousif_raiyan_pip_package-1.8.6.dist-info/WHEEL
yousif_raiyan_pip_package-1.8.6.dist-info/top_level.txt
yousif_raiyan_pip_package-1.8.6.dist-info/RECORD
