Metadata-Version: 2.4
Name: yousif_raiyan_pip_package
Version: 1.8.6
Summary: Comprehensive EEG analysis pipeline with advanced spectral analysis, connectivity analysis, memory-safe HDF5 graph processing, trigger detection, and spectral parameterization (FOOOF/SpecParam)
Author-email: Raiyan <raiyan0511@gmail.com>
Maintainer-email: Raiyan <raiyan0511@gmail.com>
Project-URL: Homepage, https://github.com/raiyanUofT/yousif_raiyan_pip_package
Project-URL: Repository, https://github.com/raiyanUofT/yousif_raiyan_pip_package
Project-URL: Issues, https://github.com/raiyanUofT/yousif_raiyan_pip_package/issues
Project-URL: Documentation, https://github.com/raiyanUofT/yousif_raiyan_pip_package#readme
Keywords: eeg,signal-processing,neuroscience,spectral-analysis,connectivity-analysis,graph-analysis,coherence,correlation,fooof,specparam,spectral-parameterization,aperiodic,oscillations,hdf5,memory-safe,large-files,multi-band,frequency-bands
Classifier: Development Status :: 4 - Beta
Classifier: Intended Audience :: Science/Research
Classifier: Intended Audience :: Healthcare Industry
Classifier: License :: OSI Approved :: MIT License
Classifier: Programming Language :: Python :: 3
Classifier: Programming Language :: Python :: 3.7
Classifier: Programming Language :: Python :: 3.8
Classifier: Programming Language :: Python :: 3.9
Classifier: Programming Language :: Python :: 3.10
Classifier: Programming Language :: Python :: 3.11
Classifier: Topic :: Scientific/Engineering :: Medical Science Apps.
Classifier: Topic :: Scientific/Engineering :: Information Analysis
Classifier: Topic :: Software Development :: Libraries :: Python Modules
Classifier: Operating System :: OS Independent
Requires-Python: >=3.7
License-File: LICENSE
Requires-Dist: numpy
Requires-Dist: scipy
Requires-Dist: mne
Requires-Dist: pyedflib
Requires-Dist: matplotlib
Requires-Dist: seaborn
Requires-Dist: pandas
Requires-Dist: opencv-python
Requires-Dist: torch
Requires-Dist: torchvision
Requires-Dist: joblib
Requires-Dist: scikit-learn
Requires-Dist: Pillow
Requires-Dist: specparam
Requires-Dist: fooof
Requires-Dist: h5py
Requires-Dist: tqdm
Provides-Extra: dev
Requires-Dist: build; extra == "dev"
Requires-Dist: twine; extra == "dev"
Requires-Dist: bump2version; extra == "dev"
Dynamic: license-file
